alphakek/__init__.py
alphakek/_base_client.py
alphakek/_client.py
alphakek/_compat.py
alphakek/_constants.py
alphakek/_exceptions.py
alphakek/_files.py
alphakek/_models.py
alphakek/_qs.py
alphakek/_resource.py
alphakek/_response.py
alphakek/_streaming.py
alphakek/_types.py
alphakek/_version.py
alphakek/py.typed
alphakek/_utils/__init__.py
alphakek/_utils/_logs.py
alphakek/_utils/_proxy.py
alphakek/_utils/_streams.py
alphakek/_utils/_sync.py
alphakek/_utils/_transform.py
alphakek/_utils/_typing.py
alphakek/_utils/_utils.py
alphakek/lib/.keep
alphakek/resources/__init__.py
alphakek/resources/account.py
alphakek/resources/knowledge.py
alphakek/resources/visuals.py
alphakek/types/__init__.py
alphakek/types/knowledge_ask_params.py
alphakek/types/knowledge_ask_response.py
alphakek/types/knowledge_document_view.py
alphakek/types/knowledge_get_by_link_params.py
alphakek/types/knowledge_search_params.py
alphakek/types/knowledge_search_response.py
alphakek/types/user.py
alphakek/types/visual_apply_effect_params.py
alphakek/types/visual_apply_mirage_params.py
alphakek/types/visual_create_image_params.py
alphakek-0.1.0a5.dist-info/METADATA
alphakek-0.1.0a5.dist-info/WHEEL
alphakek-0.1.0a5.dist-info/licenses/LICENSE
alphakek-0.1.0a5.dist-info/RECORD
